task4/lfsr.sv
module lfsr(
    input logic           clk,         // input clock
    input logic           rst,         // reset
    input logic           en,           // enable
    output logic [7:0]    data_out     // serial data out
    );          // end of port list

     logic [8:1]     sreg;       // shift register

    always_ff @ (posedge clk)
        if (rst)
            sreg <= 8'b1;
        else if (en)
            sreg <= {sreg[7:1], sreg[7] ^ sreg[3]};
        
    assign data_out = sreg;
endmodule

task4/clktick.sv
module clktick #(
	parameter WIDTH = 16
)(
  // interface signals
  input  logic             clk,      // clock 
  input  logic             rst,      // reset
  input  logic             en,       // enable signal
  input  logic [WIDTH-1:0] N,     	 // clock divided by N+1 (N= 16)
  output logic  		       tick      // tick output
);

logic [WIDTH-1:0] count;

always_ff @ (posedge clk)
    if (rst) begin
        tick <= 1'b0;
        count <= N;  
        end
    else if (en) begin
	    if (count == 0) begin
		    tick <= 1'b1;
		    count <= N;
	        end
	    else begin
		    tick <= 1'b0;
		    count <= count - 1'b1;
	        end
        end
endmodule

task4/f1_fsm.sv
module f1_fsm (
    input logic         clk,         // clock signal
    input logic         rst,         // reset
    input logic         en,          // enable
    input logic         trigger,     // trigger
    output logic        cmd_seq,     // high during the sequence of data
    output logic        cmd_delay,   // triggers start of delay sequence
    output logic [7:0]  data_out     // output
);

    // define our states
    typedef enum {S0, S1, S2, S3, S4, S5, S6, S7, S8} my_state;
    my_state current_state, next_state;

    // state transitions
    always_ff @(posedge clk)
        if (rst)              current_state <= S0;
        else     current_state <= next_state;

    // next state logic
    always_comb
    case (current_state)
        S0:     if ((en == 1'b1) && (trigger == 1'b1))     next_state = S1;
                else                next_state = current_state;
        S1:     if (en == 1'b1)     next_state = S2;
                else                next_state = current_state;
        S2:     if (en == 1'b1)     next_state = S3;
                else                next_state = current_state;
        S3:     if (en == 1'b1)     next_state = S4;
                else                next_state = current_state;
        S4:     if (en == 1'b1)     next_state = S5;
                else                next_state = current_state;
        S5:     if (en == 1'b1)     next_state = S6;
                else                next_state = current_state;
        S6:     if (en == 1'b1)     next_state = S7;
                else                next_state = current_state;
        S7:     if (en == 1'b1)     next_state = S8;
                else                next_state = current_state;
        S8:     if (en == 1'b1)     next_state = S0;
                else                next_state = current_state;
        default: next_state = S0;
    endcase

    //  output logic
    always_comb
        case (current_state)
            S0: begin     
                        data_out = 8'b0;
                        cmd_seq = 1'b1;
                        cmd_delay = 1'b0;
                end  

            S1:     data_out = 8'b1;
            S2:     data_out = 8'b11;
            S3:     data_out = 8'b111;
            S4:     data_out = 8'b1111;
            S5:     data_out = 8'b11111;
            S6:     data_out = 8'b111111;
            S7:     data_out = 8'b1111111;
            S8: begin
                        data_out = 8'b11111111;
                        cmd_seq = 1'b0;
                        cmd_delay = 1'b1;
                end
        endcase
endmodule

task4/delay.sv
module delay #(
	parameter WIDTH = 8    // no of bits in delay counter
)(
    input   logic               clk,        // clock signal
    input   logic               rst,        // reset signal
    input   logic               trigger,    // trigger input signal
    input   logic [WIDTH-1:0]   n,          // no of clock cycle delay
    output  logic               time_out    // output pulse signal
);
    // Declare counter
    logic [WIDTH-1:0]   count = {WIDTH{1'b0}};            // internal counter

    // Define our states
    typedef enum {IDLE, COUNTING, TIME_OUT, WAIT_LOW}  my_state;
    my_state current_state, next_state;

    // counter
    always_ff @(posedge clk)
        if (rst | trigger | count=={WIDTH{1'b0}}) count <= n - 1'b1;
        else                                count <= count - 1'b1;

    // state transition
    always_ff @(posedge clk)
        if (rst)    current_state <= IDLE;
        else        current_state <= next_state; 

    // next state logic
    always_comb
        case (current_state)
            IDLE:       if (trigger==1'b1)  next_state = COUNTING;
                        else    next_state = current_state;
            COUNTING:   if (count=={WIDTH{1'b0}}) next_state = TIME_OUT;
                        else    next_state = current_state;
            TIME_OUT:   if (trigger==1'b1)  next_state = WAIT_LOW;
                        else    next_state = IDLE;
            WAIT_LOW:   if (trigger==1'b0)  next_state = IDLE;
                        else    next_state = current_state;
            default: next_state = IDLE;
        endcase
    
    // output logic
    always_comb
        case (current_state)
            IDLE:       time_out = 1'b0;
            COUNTING:   time_out = 1'b0;
            TIME_OUT:   time_out = 1'b1;
            WAIT_LOW:   time_out = 1'b0;
            default:    time_out = 1'b0;
        endcase
endmodule

task4/f1_lights.sv
module f1_lights #(
        parameter   N_WIDTH = 16,
                    D_WIDTH = 8,
                    K_WIDTH = 8
    )(
        input logic                 clk,
        input logic                 rst,
        input logic                 en,
        input logic [N_WIDTH-1:0]   N,
        input logic                 trigger,
        output logic [D_WIDTH-1:0]  data_out
    );

        //interconnect wires
        logic                   seq;
        logic                   delay;
        logic [K_WIDTH-1:0]     k;
        logic                   i1;
        logic                   i0;
        logic                   mux_out;

    always_comb begin
        mux_out = seq ? i1 : i0;
    end

    delay randon_delay (
        .clk(clk),
        .rst(rst),
        .trigger(delay),
        .n(k),
        .time_out(i0)
    );

    f1_fsm f1 (
        .clk(clk),
        .rst(rst),
        .en(mux_out),
        .trigger(trigger),
        .cmd_seq(seq),
        .cmd_delay(delay),
        .data_out(data_out)
    );

    clktick clocktick (
        .clk(clk),
        .rst(rst),
        .en(seq),
        .N(N),
        .tick(i1)
    );

    lfsr f1_lfsr(
        .clk(clk),
        .rst(rst),
        .en(en),
        .data_out(k)
    );

endmodule

task4/f1_lights.vcd
$version Generated by VerilatedVcd $end
$date Thu Nov 16 13:57:15 2023 $end
$timescale 1ps $end

 $scope module TOP $end
  $var wire 16 1 N [15:0] $end
  $var wire  1 . clk $end
  $var wire  8 3 data_out [7:0] $end
  $var wire  1 0 en $end
  $var wire  1 / rst $end
  $var wire  1 2 trigger $end
  $scope module f1_lights $end
   $var wire 32 6 D_WIDTH [31:0] $end
   $var wire 32 6 K_WIDTH [31:0] $end
   $var wire 16 1 N [15:0] $end
   $var wire 32 5 N_WIDTH [31:0] $end
   $var wire  1 . clk $end
   $var wire  8 3 data_out [7:0] $end
   $var wire  1 $ delay $end
   $var wire  1 0 en $end
   $var wire  1 ' i0 $end
   $var wire  1 & i1 $end
   $var wire  8 % k [7:0] $end
   $var wire  1 ( mux_out $end
   $var wire  1 / rst $end
   $var wire  1 # seq $end
   $var wire  1 2 trigger $end
   $scope module clocktick $end
    $var wire 16 1 N [15:0] $end
    $var wire 32 5 WIDTH [31:0] $end
    $var wire  1 . clk $end
    $var wire 16 ) count [15:0] $end
    $var wire  1 # en $end
    $var wire  1 / rst $end
    $var wire  1 & tick $end
   $upscope $end
   $scope module f1 $end
    $var wire  1 . clk $end
    $var wire  1 $ cmd_delay $end
    $var wire  1 # cmd_seq $end
    $var wire 32 * current_state [31:0] $end
    $var wire  8 3 data_out [7:0] $end
    $var wire  1 ( en $end
    $var wire 32 4 next_state [31:0] $end
    $var wire  1 / rst $end
    $var wire  1 2 trigger $end
   $upscope $end
   $scope module f1_lfsr $end
    $var wire  1 . clk $end
    $var wire  8 % data_out [7:0] $end
    $var wire  1 0 en $end
    $var wire  1 / rst $end
    $var wire  8 % sreg [8:1] $end
   $upscope $end
   $scope module randon_delay $end
    $var wire 32 6 WIDTH [31:0] $end
    $var wire  1 . clk $end
    $var wire  8 + count [7:0] $end
    $var wire 32 , current_state [31:0] $end
    $var wire  8 % n [7:0] $end
    $var wire 32 - next_state [31:0] $end
    $var wire  1 / rst $end
    $var wire  1 ' time_out $end
    $var wire  1 $ trigger $end
   $upscope $end
  $upscope $end
 $upscope $end
$enddefinitions $end


#0
0#
0$
b00000000 %
0&
0'
0(
b0000000000000000 )
b00000000000000000000000000000000 *
b00000000 +
b00000000000000000000000000000000 ,
b00000000000000000000000000000000 -
1.
0/
10
b0000000000010000 1
12
b00000000 3
b00000000000000000000000000000000 4
b00000000000000000000000000010000 5
b00000000000000000000000000001000 6
#1
1#
0.
#2
1&
1(
b0000000000010000 )
b11111111 +
1.
1/
02
b00000000000000000000000000000001 4
#3
0.
b00000000000000000000000000000000 4
#4
b00000001 %
0&
0(
1.
#5
0.
#6
b00000000 +
1.
0/
#7
0.
#8
b00000010 %
b0000000000001111 )
1.
#9
0.
#10
b00000100 %
b0000000000001110 )
b00000001 +
1.
#11
0.
#12
b00001001 %
b0000000000001101 )
b00000000 +
1.
#13
0.
#14
b00010010 %
b0000000000001100 )
b00001000 +
1.
#15
0.
#16
b00100100 %
b0000000000001011 )
b00000111 +
1.
#17
0.
#18
b01001001 %
b0000000000001010 )
b00000110 +
1.
#19
0.
#20
b10010011 %
b0000000000001001 )
b00000101 +
1.
#21
0.
#22
b00100110 %
b0000000000001000 )
b00000100 +
1.
#23
0.
#24
b01001101 %
b0000000000000111 )
b00000011 +
1.
#25
0.
#26
b10011010 %
b0000000000000110 )
b00000010 +
1.
#27
0.
#28
b00110100 %
b0000000000000101 )
b00000001 +
1.
#29
0.
#30
b01101001 %
b0000000000000100 )
b00000000 +
1.
#31
0.
#32
b11010011 %
b0000000000000011 )
b01101000 +
1.
#33
0.
#34
b10100111 %
b0000000000000010 )
b01100111 +
1.
#35
0.
#36
b01001111 %
b0000000000000001 )
b01100110 +
1.
#37
0.
#38
b10011110 %
b0000000000000000 )
b01100101 +
1.
#39
0.
#40
b00111101 %
1&
1(
b0000000000010000 )
b01100100 +
1.
#41
0.
#42
b01111011 %
0&
0(
b0000000000001111 )
b01100011 +
1.
#43
0.
#44
b11110111 %
b0000000000001110 )
b01100010 +
1.
#45
0.
#46
b11101110 %
b0000000000001101 )
b01100001 +
1.
#47
0.
#48
b11011100 %
b0000000000001100 )
b01100000 +
1.
#49
0.
#50
b10111000 %
b0000000000001011 )
b01011111 +
1.
#51
0.
#52
b01110000 %
b0000000000001010 )
b01011110 +
1.
#53
0.
#54
b11100001 %
b0000000000001001 )
b01011101 +
1.
#55
0.
#56
b11000011 %
b0000000000001000 )
b01011100 +
1.
#57
0.
#58
b10000111 %
b0000000000000111 )
b01011011 +
1.
#59
0.
#60
b00001111 %
b0000000000000110 )
b01011010 +
1.
#61
0.
#62
b00011111 %
b0000000000000101 )
b01011001 +
1.
#63
0.
#64
b00111111 %
b0000000000000100 )
b01011000 +
1.
#65
0.
#66
b01111111 %
b0000000000000011 )
b01010111 +
1.
#67
0.
#68
b11111110 %
b0000000000000010 )
b01010110 +
1.
#69
0.
#70
b11111100 %
b0000000000000001 )
b01010101 +
1.
#71
0.
#72
b11111000 %
b0000000000000000 )
b01010100 +
1.
#73
0.
#74
b11110001 %
1&
1(
b0000000000010000 )
b01010011 +
1.
#75
0.
#76
b11100011 %
0&
0(
b0000000000001111 )
b01010010 +
1.
#77
0.
#78
b11000111 %
b0000000000001110 )
b01010001 +
1.
#79
0.
#80
b10001110 %
b0000000000001101 )
b01010000 +
1.
#81
0.
#82
b00011101 %
b0000000000001100 )
b01001111 +
1.
#83
0.
#84
b00111011 %
b0000000000001011 )
b01001110 +
1.
#85
0.
#86
b01110110 %
b0000000000001010 )
b01001101 +
1.
#87
0.
#88
b11101100 %
b0000000000001001 )
b01001100 +
1.
12
#89
0.
#90
b11011000 %
b0000000000001000 )
b01001011 +
1.
02
#91
0.
#92
b10110001 %
b0000000000000111 )
b01001010 +
1.
#93
0.
#94
b01100010 %
b0000000000000110 )
b01001001 +
1.
#95
0.
#96
b11000101 %
b0000000000000101 )
b01001000 +
1.
#97
0.
#98
b10001010 %
b0000000000000100 )
b01000111 +
1.
#99
0.
#100
b00010100 %
b0000000000000011 )
b01000110 +
1.
#101
0.
#102
b00101001 %
b0000000000000010 )
b01000101 +
1.
#103
0.
#104
b01010010 %
b0000000000000001 )
b01000100 +
1.
#105
0.
#106
b10100101 %
b0000000000000000 )
b01000011 +
1.
#107
0.
#108
b01001011 %
1&
1(
b0000000000010000 )
b01000010 +
1.
#109
0.
#110
b10010111 %
0&
0(
b0000000000001111 )
b01000001 +
1.
#111
0.
#112
b00101111 %
b0000000000001110 )
b01000000 +
1.
#113
0.
#114
b01011111 %
b0000000000001101 )
b00111111 +
1.
#115
0.
#116
b10111110 %
b0000000000001100 )
b00111110 +
1.
#117
0.
#118
b01111101 %
b0000000000001011 )
b00111101 +
1.
#119
0.
#120
b11111010 %
b0000000000001010 )
b00111100 +
1.
#121
0.
#122
b11110101 %
b0000000000001001 )
b00111011 +
1.
#123
0.
#124
b11101010 %
b0000000000001000 )
b00111010 +
1.
#125
0.
#126
b11010101 %
b0000000000000111 )
b00111001 +
1.
#127
0.
#128
b10101010 %
b0000000000000110 )
b00111000 +
1.
#129
0.
#130
b01010100 %
b0000000000000101 )
b00110111 +
1.
#131
0.
#132
b10101000 %
b0000000000000100 )
b00110110 +
1.
#133
0.
#134
b01010000 %
b0000000000000011 )
b00110101 +
1.
#135
0.
#136
b10100001 %
b0000000000000010 )
b00110100 +
1.
#137
0.
#138
b01000010 %
b0000000000000001 )
b00110011 +
1.
#139
0.
#140
b10000101 %
b0000000000000000 )
b00110010 +
1.
#141
0.
#142
b00001011 %
1&
1(
b0000000000010000 )
b00110001 +
1.
#143
0.
#144
b00010110 %
0&
0(
b0000000000001111 )
b00110000 +
1.
#145
0.
#146
b00101101 %
b0000000000001110 )
b00101111 +
1.
#147
0.
#148
b01011011 %
b0000000000001101 )
b00101110 +
1.
#149
0.
#150
b10110111 %
b0000000000001100 )
b00101101 +
1.
#151
0.
#152
b01101111 %
b0000000000001011 )
b00101100 +
1.
#153
0.
#154
b11011110 %
b0000000000001010 )
b00101011 +
1.
#155
0.
#156
b10111100 %
b0000000000001001 )
b00101010 +
1.
#157
0.
#158
b01111001 %
b0000000000001000 )
b00101001 +
1.
#159
0.
#160
b11110011 %
b0000000000000111 )
b00101000 +
1.
#161
0.
#162
b11100111 %
b0000000000000110 )
b00100111 +
1.
#163
0.
#164
b11001110 %
b0000000000000101 )
b00100110 +
1.
#165
0.
#166
b10011100 %
b0000000000000100 )
b00100101 +
1.
#167
0.
#168
b00111001 %
b0000000000000011 )
b00100100 +
1.
#169
0.
#170
b01110010 %
b0000000000000010 )
b00100011 +
1.
#171
0.
#172
b11100101 %
b0000000000000001 )
b00100010 +
1.
#173
0.
#174
b11001010 %
b0000000000000000 )
b00100001 +
1.
#175
0.
#176
b10010101 %
1&
1(
b0000000000010000 )
b00100000 +
1.
#177
0.
#178
b00101011 %
0&
0(
b0000000000001111 )
b00011111 +
1.
#179
0.
#180
b01010110 %
b0000000000001110 )
b00011110 +
1.
#181
0.
#182
b10101100 %
b0000000000001101 )
b00011101 +
1.
#183
0.
#184
b01011001 %
b0000000000001100 )
b00011100 +
1.
#185
0.
#186
b10110011 %
b0000000000001011 )
b00011011 +
1.
#187
0.
#188
b01100110 %
b0000000000001010 )
b00011010 +
1.
#189
0.
#190
b11001100 %
b0000000000001001 )
b00011001 +
1.
#191
0.
#192
b10011000 %
b0000000000001000 )
b00011000 +
1.
#193
0.
#194
b00110000 %
b0000000000000111 )
b00010111 +
1.
#195
0.
#196
b01100000 %
b0000000000000110 )
b00010110 +
1.
#197
0.
#198
b11000001 %
b0000000000000101 )
b00010101 +
1.
#199
0.
#200
b10000011 %
b0000000000000100 )
b00010100 +
1.
#201
0.
#202
b00000110 %
b0000000000000011 )
b00010011 +
1.
#203
0.
#204
b00001101 %
b0000000000000010 )
b00010010 +
1.
#205
0.
#206
b00011011 %
b0000000000000001 )
b00010001 +
1.
#207
0.
#208
b00110110 %
b0000000000000000 )
b00010000 +
1.
12
#209
0.
#210
b01101101 %
1&
1(
b0000000000010000 )
b00001111 +
1.
02
b00000000000000000000000000000001 4
#211
0.
b00000000000000000000000000000000 4
#212
b11011010 %
0&
0(
b0000000000001111 )
b00001110 +
1.
#213
0.
#214
b10110101 %
b0000000000001110 )
b00001101 +
1.
#215
0.
#216
b01101011 %
b0000000000001101 )
b00001100 +
1.
#217
0.
#218
b11010111 %
b0000000000001100 )
b00001011 +
1.
#219
0.
#220
b10101110 %
b0000000000001011 )
b00001010 +
1.
#221
0.
#222
b01011101 %
b0000000000001010 )
b00001001 +
1.
#223
0.
#224
b10111010 %
b0000000000001001 )
b00001000 +
1.
#225
0.
#226
b01110100 %
b0000000000001000 )
b00000111 +
1.
#227
0.
#228
b11101000 %
b0000000000000111 )
b00000110 +
1.
#229
0.
#230
b11010001 %
b0000000000000110 )
b00000101 +
1.
#231
0.
#232
b10100011 %
b0000000000000101 )
b00000100 +
1.
#233
0.
#234
b01000110 %
b0000000000000100 )
b00000011 +
1.
#235
0.
#236
b10001100 %
b0000000000000011 )
b00000010 +
1.
#237
0.
#238
b00011001 %
b0000000000000010 )
b00000001 +
1.
#239
0.
#240
b00110010 %
b0000000000000001 )
b00000000 +
1.
#241
0.
#242
b01100100 %
b0000000000000000 )
b00110001 +
1.
#243
0.
#244
b11001000 %
1&
1(
b0000000000010000 )
b00110000 +
1.
#245
0.
#246
b10010001 %
0&
0(
b0000000000001111 )
b00101111 +
1.
#247
0.
#248
b00100010 %
b0000000000001110 )
b00101110 +
1.
#249
0.
#250
b01000100 %
b0000000000001101 )
b00101101 +
1.
#251
0.
#252
b10001000 %
b0000000000001100 )
b00101100 +
1.
#253
0.
#254
b00010000 %
b0000000000001011 )
b00101011 +
1.
#255
0.
#256
b00100000 %
b0000000000001010 )
b00101010 +
1.
#257
0.
#258
b01000000 %
b0000000000001001 )
b00101001 +
1.
#259
0.
#260
b10000001 %
b0000000000001000 )
b00101000 +
1.
#261
0.
#262
b00000010 %
b0000000000000111 )
b00100111 +
1.
#263
0.
#264
b00000100 %
b0000000000000110 )
b00100110 +
1.
#265
0.
#266
b00001001 %
b0000000000000101 )
b00100101 +
1.
#267
0.
#268
b00010010 %
b0000000000000100 )
b00100100 +
1.
#269
0.
#270
b00100100 %
b0000000000000011 )
b00100011 +
1.
#271
0.
#272
b01001001 %
b0000000000000010 )
b00100010 +
1.
#273
0.
#274
b10010011 %
b0000000000000001 )
b00100001 +
1.
#275
0.
#276
b00100110 %
b0000000000000000 )
b00100000 +
1.
#277
0.
#278
b01001101 %
1&
1(
b0000000000010000 )
b00011111 +
1.
#279
0.
#280
b10011010 %
0&
0(
b0000000000001111 )
b00011110 +
1.
12
#281
0.
#282
b00110100 %
b0000000000001110 )
b00011101 +
1.
02
#283
0.
#284
b01101001 %
b0000000000001101 )
b00011100 +
1.
#285
0.
#286
b11010011 %
b0000000000001100 )
b00011011 +
1.
#287
0.
#288
b10100111 %
b0000000000001011 )
b00011010 +
1.
#289
0.
#290
b01001111 %
b0000000000001010 )
b00011001 +
1.
#291
0.
#292
b10011110 %
b0000000000001001 )
b00011000 +
1.
#293
0.
#294
b00111101 %
b0000000000001000 )
b00010111 +
1.
#295
0.
#296
b01111011 %
b0000000000000111 )
b00010110 +
1.
#297
0.
#298
b11110111 %
b0000000000000110 )
b00010101 +
1.
#299
0.
#300
b11101110 %
b0000000000000101 )
b00010100 +
1.
#301
0.
#302
b11011100 %
b0000000000000100 )
b00010011 +
1.
#303
0.
#304
b10111000 %
b0000000000000011 )
b00010010 +
1.
#305
0.
#306
b01110000 %
b0000000000000010 )
b00010001 +
1.
#307
0.
#308
b11100001 %
b0000000000000001 )
b00010000 +
1.
#309
0.
#310
b11000011 %
b0000000000000000 )
b00001111 +
1.
#311
0.
#312
b10000111 %
1&
1(
b0000000000010000 )
b00001110 +
1.
#313
0.
#314
b00001111 %
0&
0(
b0000000000001111 )
b00001101 +
1.
#315
0.
#316
b00011111 %
b0000000000001110 )
b00001100 +
1.
#317
0.
#318
b00111111 %
b0000000000001101 )
b00001011 +
1.
#319
0.
#320
b01111111 %
b0000000000001100 )
b00001010 +
1.
#321
0.
#322
b11111110 %
b0000000000001011 )
b00001001 +
1.
#323
0.
#324
b11111100 %
b0000000000001010 )
b00001000 +
1.
#325
0.
#326
b11111000 %
b0000000000001001 )
b00000111 +
1.
#327
0.
#328
b11110001 %
b0000000000001000 )
b00000110 +
1.
#329
0.
#330
b11100011 %
b0000000000000111 )
b00000101 +
1.
#331
0.
#332
b11000111 %
b0000000000000110 )
b00000100 +
1.
#333
0.
#334
b10001110 %
b0000000000000101 )
b00000011 +
1.
12
#335
0.
#336
b00011101 %
b0000000000000100 )
b00000010 +
1.
02
#337
0.
#338
b00111011 %
b0000000000000011 )
b00000001 +
1.
#339
0.
#340
b01110110 %
b0000000000000010 )
b00000000 +
1.
#341
0.
#342
b11101100 %
b0000000000000001 )
b01110101 +
1.
12
#343
0.
#344
b11011000 %
b0000000000000000 )
b01110100 +
1.
02
#345
0.
#346
b10110001 %
1&
1(
b0000000000010000 )
b01110011 +
1.
#347
0.
#348
b01100010 %
0&
0(
b0000000000001111 )
b01110010 +
1.
12
#349
0.
#350
b11000101 %
b0000000000001110 )
b01110001 +
1.
02
#351
0.
#352
b10001010 %
b0000000000001101 )
b01110000 +
1.
#353
0.
#354
b00010100 %
b0000000000001100 )
b01101111 +
1.
12
#355
0.
#356
b00101001 %
b0000000000001011 )
b01101110 +
1.
02
#357
0.
#358
b01010010 %
b0000000000001010 )
b01101101 +
1.
#359
0.
#360
b10100101 %
b0000000000001001 )
b01101100 +
1.
12
#361
0.
#362
b01001011 %
b0000000000001000 )
b01101011 +
1.
02
#363
0.
#364
b10010111 %
b0000000000000111 )
b01101010 +
1.
#365
0.
#366
b00101111 %
b0000000000000110 )
b01101001 +
1.
#367
0.
#368
b01011111 %
b0000000000000101 )
b01101000 +
1.
#369
0.
#370
b10111110 %
b0000000000000100 )
b01100111 +
1.
#371
0.
#372
b01111101 %
b0000000000000011 )
b01100110 +
1.
#373
0.
#374
b11111010 %
b0000000000000010 )
b01100101 +
1.
#375
0.
#376
b11110101 %
b0000000000000001 )
b01100100 +
1.
#377
0.
#378
b11101010 %
b0000000000000000 )
b01100011 +
1.
#379
0.
#380
b11010101 %
1&
1(
b0000000000010000 )
b01100010 +
1.
#381
0.
#382
b10101010 %
0&
0(
b0000000000001111 )
b01100001 +
1.
#383
0.
#384
b01010100 %
b0000000000001110 )
b01100000 +
1.
#385
0.
#386
b10101000 %
b0000000000001101 )
b01011111 +
1.
#387
0.
#388
b01010000 %
b0000000000001100 )
b01011110 +
1.
#389
0.
#390
b10100001 %
b0000000000001011 )
b01011101 +
1.
#391
0.
#392
b01000010 %
b0000000000001010 )
b01011100 +
1.
#393
0.
#394
b10000101 %
b0000000000001001 )
b01011011 +
1.
#395
0.
#396
b00001011 %
b0000000000001000 )
b01011010 +
1.
#397
0.
#398
b00010110 %
b0000000000000111 )
b01011001 +
1.
#399
0.
#400
b00101101 %
b0000000000000110 )
b01011000 +
1.
#401
0.
#402
b01011011 %
b0000000000000101 )
b01010111 +
1.
#403
0.
#404
b10110111 %
b0000000000000100 )
b01010110 +
1.
#405
0.
#406
b01101111 %
b0000000000000011 )
b01010101 +
1.
#407
0.
#408
b11011110 %
b0000000000000010 )
b01010100 +
1.
#409
0.
#410
b10111100 %
b0000000000000001 )
b01010011 +
1.
#411
0.
#412
b01111001 %
b0000000000000000 )
b01010010 +
1.
#413
0.
#414
b11110011 %
1&
1(
b0000000000010000 )
b01010001 +
1.
#415
0.
#416
b11100111 %
0&
0(
b0000000000001111 )
b01010000 +
1.
#417
0.
#418
b11001110 %
b0000000000001110 )
b01001111 +
1.
#419
0.
#420
b10011100 %
b0000000000001101 )
b01001110 +
1.
#421
0.
#422
b00111001 %
b0000000000001100 )
b01001101 +
1.
#423
0.
#424
b01110010 %
b0000000000001011 )
b01001100 +
1.
#425
0.
#426
b11100101 %
b0000000000001010 )
b01001011 +
1.
#427
0.
#428
b11001010 %
b0000000000001001 )
b01001010 +
1.
#429
0.
#430
b10010101 %
b0000000000001000 )
b01001001 +
1.
#431
0.
#432
b00101011 %
b0000000000000111 )
b01001000 +
1.
#433
0.
#434
b01010110 %
b0000000000000110 )
b01000111 +
1.
#435
0.
#436
b10101100 %
b0000000000000101 )
b01000110 +
1.
#437
0.
#438
b01011001 %
b0000000000000100 )
b01000101 +
1.
#439
0.
#440
b10110011 %
b0000000000000011 )
b01000100 +
1.
#441
0.
#442
b01100110 %
b0000000000000010 )
b01000011 +
1.
#443
0.
#444
b11001100 %
b0000000000000001 )
b01000010 +
1.
#445
0.
#446
b10011000 %
b0000000000000000 )
b01000001 +
1.
#447
0.
#448
b00110000 %
1&
1(
b0000000000010000 )
b01000000 +
1.
#449
0.
#450
b01100000 %
0&
0(
b0000000000001111 )
b00111111 +
1.
#451
0.
#452
b11000001 %
b0000000000001110 )
b00111110 +
1.
#453
0.
#454
b10000011 %
b0000000000001101 )
b00111101 +
1.
#455
0.
#456
b00000110 %
b0000000000001100 )
b00111100 +
1.
#457
0.
#458
b00001101 %
b0000000000001011 )
b00111011 +
1.
#459
0.
#460
b00011011 %
b0000000000001010 )
b00111010 +
1.
#461
0.
#462
b00110110 %
b0000000000001001 )
b00111001 +
1.
#463
0.
#464
b01101101 %
b0000000000001000 )
b00111000 +
1.
#465
0.
#466
b11011010 %
b0000000000000111 )
b00110111 +
1.
#467
0.
#468
b10110101 %
b0000000000000110 )
b00110110 +
1.
#469
0.
#470
b01101011 %
b0000000000000101 )
b00110101 +
1.
#471
0.
#472
b11010111 %
b0000000000000100 )
b00110100 +
1.
#473
0.
#474
b10101110 %
b0000000000000011 )
b00110011 +
1.
#475
0.
#476
b01011101 %
b0000000000000010 )
b00110010 +
1.
#477
0.
#478
b10111010 %
b0000000000000001 )
b00110001 +
1.
#479
0.
#480
b01110100 %
b0000000000000000 )
b00110000 +
1.
#481
0.
#482
b11101000 %
1&
1(
b0000000000010000 )
b00101111 +
1.
#483
0.
#484
b11010001 %
0&
0(
b0000000000001111 )
b00101110 +
1.
#485
0.
#486
b10100011 %
b0000000000001110 )
b00101101 +
1.
#487
0.
#488
b01000110 %
b0000000000001101 )
b00101100 +
1.
#489
0.
#490
b10001100 %
b0000000000001100 )
b00101011 +
1.
12
#491
0.
#492
b00011001 %
b0000000000001011 )
b00101010 +
1.
02
#493
0.
#494
b00110010 %
b0000000000001010 )
b00101001 +
1.
#495
0.
#496
b01100100 %
b0000000000001001 )
b00101000 +
1.
#497
0.
#498
b11001000 %
b0000000000001000 )
b00100111 +
1.
12
#499
0.
#500
b10010001 %
b0000000000000111 )
b00100110 +
1.
02
#501
0.
#502
b00100010 %
b0000000000000110 )
b00100101 +
1.
#503
0.
#504
b01000100 %
b0000000000000101 )
b00100100 +
1.
#505
0.
#506
b10001000 %
b0000000000000100 )
b00100011 +
1.
12
#507
0.
#508
b00010000 %
b0000000000000011 )
b00100010 +
1.
02
#509
0.
#510
b00100000 %
b0000000000000010 )
b00100001 +
1.
#511
0.
#512
b01000000 %
b0000000000000001 )
b00100000 +
1.
#513
0.
#514
b10000001 %
b0000000000000000 )
b00011111 +
1.
#515
0.
#516
b00000010 %
1&
1(
b0000000000010000 )
b00011110 +
1.
#517
0.
#518
b00000100 %
0&
0(
b0000000000001111 )
b00011101 +
1.
#519
0.
#520
b00001001 %
b0000000000001110 )
b00011100 +
1.
#521
0.
#522
b00010010 %
b0000000000001101 )
b00011011 +
1.
#523
0.
#524
b00100100 %
b0000000000001100 )
b00011010 +
1.
#525
0.
#526
b01001001 %
b0000000000001011 )
b00011001 +
1.
#527
0.
#528
b10010011 %
b0000000000001010 )
b00011000 +
1.
#529
0.
#530
b00100110 %
b0000000000001001 )
b00010111 +
1.
#531
0.
#532
b01001101 %
b0000000000001000 )
b00010110 +
1.
#533
0.
#534
b10011010 %
b0000000000000111 )
b00010101 +
1.
#535
0.
#536
b00110100 %
b0000000000000110 )
b00010100 +
1.
#537
0.
#538
b01101001 %
b0000000000000101 )
b00010011 +
1.
#539
0.
#540
b11010011 %
b0000000000000100 )
b00010010 +
1.
#541
0.
#542
b10100111 %
b0000000000000011 )
b00010001 +
1.
#543
0.
#544
b01001111 %
b0000000000000010 )
b00010000 +
1.
#545
0.
#546
b10011110 %
b0000000000000001 )
b00001111 +
1.
#547
0.
#548
b00111101 %
b0000000000000000 )
b00001110 +
1.
#549
0.
#550
b01111011 %
1&
1(
b0000000000010000 )
b00001101 +
1.
#551
0.
#552
b11110111 %
0&
0(
b0000000000001111 )
b00001100 +
1.
#553
0.
#554
b11101110 %
b0000000000001110 )
b00001011 +
1.
#555
0.
#556
b11011100 %
b0000000000001101 )
b00001010 +
1.
#557
0.
#558
b10111000 %
b0000000000001100 )
b00001001 +
1.
#559
0.
#560
b01110000 %
b0000000000001011 )
b00001000 +
1.
#561
0.
#562
b11100001 %
b0000000000001010 )
b00000111 +
1.
#563
0.
#564
b11000011 %
b0000000000001001 )
b00000110 +
1.
#565
0.
#566
b10000111 %
b0000000000001000 )
b00000101 +
1.
#567
0.
#568
b00001111 %
b0000000000000111 )
b00000100 +
1.
#569
0.
#570
b00011111 %
b0000000000000110 )
b00000011 +
1.
#571
0.
#572
b00111111 %
b0000000000000101 )
b00000010 +
1.
#573
0.
#574
b01111111 %
b0000000000000100 )
b00000001 +
1.
#575
0.
#576
b11111110 %
b0000000000000011 )
b00000000 +
1.
#577
0.
#578
b11111100 %
b0000000000000010 )
b11111101 +
1.
#579
0.
#580
b11111000 %
b0000000000000001 )
b11111100 +
1.
#581
0.
#582
b11110001 %
b0000000000000000 )
b11111011 +
1.
#583
0.
#584
b11100011 %
1&
1(
b0000000000010000 )
b11111010 +
1.
#585
0.
#586
b11000111 %
0&
0(
b0000000000001111 )
b11111001 +
1.
#587
0.
#588
b10001110 %
b0000000000001110 )
b11111000 +
1.
#589
0.
#590
b00011101 %
b0000000000001101 )
b11110111 +
1.
#591
0.
#592
b00111011 %
b0000000000001100 )
b11110110 +
1.
#593
0.
#594
b01110110 %
b0000000000001011 )
b11110101 +
1.
#595
0.
#596
b11101100 %
b0000000000001010 )
b11110100 +
1.
#597
0.
#598
b11011000 %
b0000000000001001 )
b11110011 +
1.
#599
0.
#600
b10110001 %
b0000000000001000 )
b11110010 +
1.
#601
0.
#602
b01100010 %
b0000000000000111 )
b11110001 +
1.
12
#603
0.
